myst_nb_json/__init__.py
myst_nb_json/py.typed
myst_nb_json/resources/myst-nb-json.css
myst_nb_json/resources/myst-nb-json.js
myst_nb_json-0.1.3.dist-info/LICENSE
myst_nb_json-0.1.3.dist-info/METADATA
myst_nb_json-0.1.3.dist-info/WHEEL
myst_nb_json-0.1.3.dist-info/entry_points.txt
myst_nb_json-0.1.3.dist-info/top_level.txt
myst_nb_json-0.1.3.dist-info/RECORD
