Metadata-Version: 2.1
Name: myst-nb-json
Version: 0.1.3
Summary: A MIME-type plugin for rendering JSON output from Jupyter notebooks to HTML
Author-email: "Alexandrov Team, EMBL" <andreas.eisenbarth@embl.de>, Andreas Eisenbarth <andreas.eisenbarth@embl.de>
License: MIT
Project-URL: homepage, https://github.com/aeisenbarth/myst-nb-json/
Project-URL: repository, https://github.com/aeisenbarth/myst-nb-json.git
Project-URL: documentation, https://aeisenbarth.github.io/myst-nb-json/
Project-URL: issues, https://github.com/aeisenbarth/myst-nb-json/issues/
Project-URL: changelog, https://github.com/aeisenbarth/myst-nb-json/main/CHANGELOG.md
Keywords: docutils,sphinx,json
Classifier: Development Status :: 4 - Beta
Classifier: Framework :: Sphinx :: Extension
Classifier: Intended Audience :: Developers
Classifier: License :: OSI Approved :: BSD License
Classifier: Programming Language :: Python :: 3
Classifier: Programming Language :: Python :: 3.9
Classifier: Programming Language :: Python :: 3.10
Classifier: Programming Language :: Python :: 3.11
Classifier: Programming Language :: Python :: 3.12
Classifier: Topic :: Software Development :: Libraries :: Python Modules
Classifier: Topic :: Text Processing :: Markup
Requires-Python: >=3.9
License-File: LICENSE
Requires-Dist: docutils
Requires-Dist: myst-nb >=1.0.0
Provides-Extra: dev
Requires-Dist: mypy >=1.8.0 ; extra == 'dev'
Requires-Dist: pre-commit >=3.6.0 ; extra == 'dev'
Requires-Dist: ruff >=0.1.14 ; extra == 'dev'
Provides-Extra: docs
Requires-Dist: docutils >=0.21.2 ; extra == 'docs'
Requires-Dist: ipython >=8.12.0 ; extra == 'docs'
Requires-Dist: myst-nb >=1.0.0 ; extra == 'docs'
Requires-Dist: pydantic >=2.0 ; extra == 'docs'
Requires-Dist: Sphinx >=7.2.6 ; extra == 'docs'
Requires-Dist: sphinx-book-theme >=1.1.3 ; extra == 'docs'
Provides-Extra: test
Requires-Dist: ipython >=8.12.0 ; extra == 'test'
Requires-Dist: pytest ~=7.1 ; extra == 'test'
Requires-Dist: pytest-cov >=5.0.0 ; extra == 'test'
Requires-Dist: pytest-regressions >=2.5.0 ; extra == 'test'
Requires-Dist: selenium ~=4.22 ; extra == 'test'
Requires-Dist: Sphinx[test] >=7.2.6 ; extra == 'test'
Provides-Extra: type-hints
Requires-Dist: types-docutils >=0.21.0.20240423 ; extra == 'type-hints'
